ccipher/__init__.py
ccipher/commons.py
ccipher/decrypt.py
ccipher/decrypted.txt
ccipher/encrypt.py
ccipher/encrypted.txt
ccipher/file.py
ccipher/file.txt
ccipher/main.py
ccipher-0.0.7.dist-info/METADATA
ccipher-0.0.7.dist-info/WHEEL
ccipher-0.0.7.dist-info/licenses/LICENSE
ccipher-0.0.7.dist-info/RECORD
