Metadata-Version: 2.1
Name: ccipher
Version: 0.0.7
Summary: A package to encrypt and decrypt messages usign Caesar cipher
Project-URL: Homepage, https://github.com/marchiartur/caesar-cipher
Project-URL: Bug Tracker, https://github.com/marchiartur/caesar-cipher/issues
Author-email: Artur Marchi Pacagnan <marchiartur@gmail.com>
License-File: LICENSE
Classifier: License :: OSI Approved :: MIT License
Classifier: Operating System :: OS Independent
Classifier: Programming Language :: Python :: 3
Requires-Python: >=3.10.6
